<?xml version="1.0" encoding="utf-8"?>
<HattrickData>
  <FileName>matchorders.xml</FileName>
  <Version>3.0</Version>
  <UserID>1248859</UserID>
  <FetchedDate>2020-06-02 17:53:13</FetchedDate>
  <MatchID>658873935</MatchID>
  <IsYouth>False</IsYouth>
  <MatchData>
    <TacticType>0</TacticType>
    <TacticSkill>0</TacticSkill>
    <RatingMidfield>16</RatingMidfield>
    <RatingRightDef>17</RatingRightDef>
    <RatingMidDef>18</RatingMidDef>
    <RatingLeftDef>18</RatingLeftDef>
    <RatingRightAtt>21</RatingRightAtt>
    <RatingMidAtt>17</RatingMidAtt>
    <RatingLeftAtt>21</RatingLeftAtt>
  </MatchData>
</HattrickData>